confpickem/__init__.py
confpickem/analyze_player_skills.py
confpickem/apply_realistic_skills.py
confpickem/confidence_pickem_sim.py
confpickem/live_odds_scraper.py
confpickem/yahoo_pickem_integration.py
confpickem/yahoo_pickem_scraper.py
confpickem/cli/README.md
confpickem/cli/__init__.py
confpickem/cli/optimize.py
confpickem/cli/player_skills.py
confpickem/cli/win_probability.py
confpickem-0.3.0.dist-info/METADATA
confpickem-0.3.0.dist-info/WHEEL
confpickem-0.3.0.dist-info/entry_points.txt
confpickem-0.3.0.dist-info/licenses/LICENSE
confpickem-0.3.0.dist-info/RECORD
