Metadata-Version: 2.4
Name: confpickem
Version: 0.3.0
Summary: Simulation-based tool to analyze Confidence Pick Em pools
Project-URL: Repository, https://github.com/tefirman/confpickem
Project-URL: Documentation, https://github.com/tefirman/confpickem#readme
Project-URL: Bug Tracker, https://github.com/tefirman/confpickem/issues
Author-email: Taylor Firman <tefirman@gmail.com>
License: MIT
License-File: LICENSE
Keywords: confidence-pool,fantasy-sports,football,nfl,pick-em
Classifier: Development Status :: 3 - Alpha
Classifier: Intended Audience :: End Users/Desktop
Classifier: License :: OSI Approved :: MIT License
Classifier: Operating System :: OS Independent
Classifier: Programming Language :: Python :: 3
Classifier: Programming Language :: Python :: 3.8
Classifier: Programming Language :: Python :: 3.9
Classifier: Programming Language :: Python :: 3.10
Classifier: Programming Language :: Python :: 3.11
Classifier: Programming Language :: Python :: 3.12
Classifier: Programming Language :: Python :: 3.13
Classifier: Topic :: Games/Entertainment
Requires-Python: >=3.8
Requires-Dist: beautifulsoup4>=4.9.0
Requires-Dist: numpy>=1.19.0
Requires-Dist: pandas>=1.2.0
Requires-Dist: requests>=2.25.0
Requires-Dist: scipy>=1.6.0
Provides-Extra: dev
Requires-Dist: black>=21.0.0; extra == 'dev'
Requires-Dist: flake8>=3.9.0; extra == 'dev'
Requires-Dist: mypy>=0.900; extra == 'dev'
Requires-Dist: pytest-cov>=2.0.0; extra == 'dev'
Requires-Dist: pytest>=6.0.0; extra == 'dev'
